dir2map/__init__.py
dir2map/main.py
dir2map-2025.3.28.6.dist-info/LICENSE
dir2map-2025.3.28.6.dist-info/METADATA
dir2map-2025.3.28.6.dist-info/WHEEL
dir2map-2025.3.28.6.dist-info/entry_points.txt
dir2map-2025.3.28.6.dist-info/top_level.txt
dir2map-2025.3.28.6.dist-info/RECORD
