Metadata-Version: 2.1
Name: dir2map
Version: 2025.3.28.6
Summary: 得到目录结构.Obtain the directory structure.
Author-email: YanChengxin <yan.cheng.xin@foxmail.com>
Project-URL: Homepage, https://github.com/yanchengxin2018/dirtree
Project-URL: Issues, https://github.com/yanchengxin2018/dirtree/issues
Classifier: Programming Language :: Python :: 3
Classifier: License :: OSI Approved :: MIT License
Classifier: Operating System :: OS Independent
Requires-Python: >=3.8.20
License-File: LICENSE
